python_bidi-0.6.2.dist-info/METADATA
python_bidi-0.6.2.dist-info/WHEEL
python_bidi-0.6.2.dist-info/entry_points.txt
python_bidi-0.6.2.dist-info/licenses/LICENSE-THIRD-PARTY.yml
python_bidi-0.6.2.dist-info/licenses/COPYING
python_bidi-0.6.2.dist-info/licenses/COPYING.LESSER
python_bidi-0.6.2.dist-info/licenses/AUTHORS.rst
bidi/algorithm.py
bidi/__init__.py
bidi/wrapper.py
bidi/mirror.py
bidi/bidi.cpython-311-powerpc64le-linux-gnu.so
python_bidi-0.6.2.dist-info/RECORD
