Metadata-Version: 2.3
Name: python-bidi
Version: 0.6.2
Classifier: Development Status :: 4 - Beta
Classifier: Intended Audience :: Developers
Classifier: Operating System :: OS Independent
Classifier: License :: OSI Approved :: GNU Library or Lesser General Public License (LGPL)
Classifier: Topic :: Text Processing
Classifier: Programming Language :: Python :: 3
Classifier: Programming Language :: Python :: 3.9
Classifier: Programming Language :: Python :: 3.10
Classifier: Programming Language :: Python :: 3.11
Classifier: Programming Language :: Python :: 3.12
Requires-Dist: pytest ; extra == 'dev'
Provides-Extra: dev
License-File: LICENSE-THIRD-PARTY.yml
License-File: COPYING
License-File: COPYING.LESSER
License-File: AUTHORS.rst
Summary: Python Bidi layout wrapping the Rust crate unicode-bidi
Keywords: bidi,unicode,layout
Author: Meir Kriheli <mkriheli@gmail.com>
Author-email: Meir Kriheli <mkriheli@gmail.com>
Project-URL: Homepage, https://github.com/MeirKriheli/python-bidi
Project-URL: Repository, https://github.com/MeirKriheli/python-bidi
Project-URL: Documentation, https://python-bidi.readthedocs.io/en/latest/
Project-URL: Issues, https://github.com/MeirKriheli/python-bidi/issues
Project-URL: Changelog, https://github.com/MeirKriheli/python-bidi/blob/master/CHANGELOG.rst
